pykrack/__init__.py
pykrack/_modidx.py
pykrack/core.py
pykrack/hierarchy.py
pykrack/utils.py
pykrack-0.0.3.dist-info/LICENSE
pykrack-0.0.3.dist-info/METADATA
pykrack-0.0.3.dist-info/WHEEL
pykrack-0.0.3.dist-info/entry_points.txt
pykrack-0.0.3.dist-info/top_level.txt
pykrack-0.0.3.dist-info/RECORD
