Metadata-Version: 2.1
Name: pykrack
Version: 0.0.3
Summary: Computing Krackhardt hierarchy score on NetowrkX graphs
Home-page: https://github.com/FerranC96/pykrack
Author: FerranC96
Author-email: ferricaro@hotmail.com
License: Apache Software License 2.0
Keywords: nbdev jupyter notebook python
Classifier: Development Status :: 4 - Beta
Classifier: Intended Audience :: Developers
Classifier: Natural Language :: English
Classifier: Programming Language :: Python :: 3.7
Classifier: Programming Language :: Python :: 3.8
Classifier: Programming Language :: Python :: 3.9
Classifier: Programming Language :: Python :: 3.10
Classifier: License :: OSI Approved :: Apache Software License
Requires-Python: >=3.7
License-File: LICENSE
Requires-Dist: numpy
Requires-Dist: pandas
Requires-Dist: networkx
Requires-Dist: rpy2
Provides-Extra: dev
